oguzhan_preprocessing/__init__.py
oguzhan_preprocessing/categorical_encoder.py
oguzhan_preprocessing/data_type_converter.py
oguzhan_preprocessing/datetime_handler.py
oguzhan_preprocessing/missing_value_handler.py
oguzhan_preprocessing/outlier_handler.py
oguzhan_preprocessing/scaler.py
oguzhan_preprocessing/text_cleaner.py
oguzhan_preprocessing-0.1.0.dist-info/METADATA
oguzhan_preprocessing-0.1.0.dist-info/WHEEL
oguzhan_preprocessing-0.1.0.dist-info/top_level.txt
oguzhan_preprocessing-0.1.0.dist-info/RECORD
